syndesi/__init__.py
syndesi/__main__.py
syndesi/component.py
syndesi/version.py
syndesi/adapters/__init__.py
syndesi/adapters/adapter.py
syndesi/adapters/adapter_worker.py
syndesi/adapters/auto.py
syndesi/adapters/descriptors.py
syndesi/adapters/ip.py
syndesi/adapters/serialport.py
syndesi/adapters/stop_conditions.py
syndesi/adapters/timeout.py
syndesi/adapters/visa.py
syndesi/cli/__init__.py
syndesi/cli/console.py
syndesi/cli/shell.py
syndesi/cli/shell_tools.py
syndesi/cli/terminal.py
syndesi/cli/terminal_apps.py
syndesi/cli/terminal_tools.py
syndesi/protocols/__init__.py
syndesi/protocols/delimited.py
syndesi/protocols/modbus.py
syndesi/protocols/protocol.py
syndesi/protocols/raw.py
syndesi/protocols/scpi.py
syndesi/remote/remote.py
syndesi/scripts/__init__.py
syndesi/scripts/syndesi.py
syndesi/tools/__init__.py
syndesi/tools/errors.py
syndesi/tools/log_settings.py
syndesi/tools/logmanager.py
syndesi/tools/types.py
syndesi-0.5.0.dist-info/licenses/LICENSE
syndesi-0.5.0.dist-info/METADATA
syndesi-0.5.0.dist-info/WHEEL
syndesi-0.5.0.dist-info/entry_points.txt
syndesi-0.5.0.dist-info/top_level.txt
syndesi-0.5.0.dist-info/RECORD
