Metadata-Version: 2.4
Name: syndesi
Version: 0.5.0
Summary: Syndesi
Author-email: Sébastien Deriaz <sebastien.deriaz1@gmail.com>
License: GPL
Keywords: python,syndesi,interface,ethernet,serial,visa
Classifier: Development Status :: 3 - Alpha
Classifier: Intended Audience :: Education
Classifier: Programming Language :: Python :: 3
Classifier: Operating System :: Unix
Classifier: Operating System :: MacOS :: MacOS X
Classifier: Operating System :: Microsoft :: Windows
Requires-Python: >=3.10
License-File: LICENSE
Requires-Dist: prompt_toolkit
Requires-Dist: pyserial
Requires-Dist: rich
Requires-Dist: platformdirs
Dynamic: license-file
